quartzbio/__init__.py
quartzbio/__main__.py
quartzbio/annotate.py
quartzbio/auth.py
quartzbio/client.py
quartzbio/errors.py
quartzbio/global_search.py
quartzbio/query.py
quartzbio/version.py
quartzbio/cli/__init__.py
quartzbio/cli/auth.py
quartzbio/cli/credentials.py
quartzbio/cli/data.py
quartzbio/cli/ipython.py
quartzbio/cli/ipython_init.py
quartzbio/cli/main.py
quartzbio/cli/tutorial.md
quartzbio/cli/tutorial.py
quartzbio/contrib/__init__.py
quartzbio/contrib/dash/README.md
quartzbio/contrib/dash/__init__.py
quartzbio/contrib/dash/login.js
quartzbio/contrib/dash/oauth-redirect.js
quartzbio/contrib/dash/solvebio_auth.py
quartzbio/contrib/dash/solvebio_dash.py
quartzbio/contrib/dash/usage.py
quartzbio/contrib/dash/js/README.md
quartzbio/contrib/dash/tests/IntegrationTests.py
quartzbio/contrib/dash/tests/__init__.py
quartzbio/contrib/dash/tests/credentials.py
quartzbio/contrib/dash/tests/test_solvebio_auth.py
quartzbio/contrib/dash/tests/test_solvebio_auth_integration.py
quartzbio/contrib/dash/tests/utils.py
quartzbio/contrib/streamlit/README.md
quartzbio/contrib/streamlit/__init__.py
quartzbio/contrib/streamlit/app_example.py
quartzbio/contrib/streamlit/solvebio_auth.py
quartzbio/contrib/streamlit/solvebio_streamlit.py
quartzbio/resource/__init__.py
quartzbio/resource/apiresource.py
quartzbio/resource/application.py
quartzbio/resource/beacon.py
quartzbio/resource/beaconset.py
quartzbio/resource/dataset.py
quartzbio/resource/dataset_restore_task.py
quartzbio/resource/dataset_snapshot_task.py
quartzbio/resource/datasetcommit.py
quartzbio/resource/datasetexport.py
quartzbio/resource/datasetfield.py
quartzbio/resource/datasetimport.py
quartzbio/resource/datasetmigration.py
quartzbio/resource/datasettemplate.py
quartzbio/resource/group.py
quartzbio/resource/manifest.py
quartzbio/resource/object.py
quartzbio/resource/object_copy_task.py
quartzbio/resource/quartzbio_object.py
quartzbio/resource/savedquery.py
quartzbio/resource/task.py
quartzbio/resource/user.py
quartzbio-1.2.0.dist-info/licenses/AUTHORS
quartzbio-1.2.0.dist-info/licenses/LICENSE
quartzbio-1.2.0.dist-info/METADATA
quartzbio-1.2.0.dist-info/WHEEL
quartzbio-1.2.0.dist-info/entry_points.txt
quartzbio-1.2.0.dist-info/top_level.txt
quartzbio-1.2.0.dist-info/RECORD
